phone_num_validator/__init__.py
phone_num_validator/validator.py
phone_num_validator-0.1.0.dist-info/METADATA
phone_num_validator-0.1.0.dist-info/WHEEL
phone_num_validator-0.1.0.dist-info/RECORD
