Metadata-Version: 2.1
Name: phone-num-validator
Version: 0.1.0
Summary: 
Author: neonine2
Author-email: jerry.wang95@yahoo.ca
Requires-Python: >=3.11,<4.0
Classifier: Programming Language :: Python :: 3
Classifier: Programming Language :: Python :: 3.11
Classifier: Programming Language :: Python :: 3.12
Requires-Dist: requests (>=2.31.0,<3.0.0)
